main.py
flowguide-0.0.1.dist-info/METADATA
flowguide-0.0.1.dist-info/WHEEL
flowguide-0.0.1.dist-info/top_level.txt
flowguide-0.0.1.dist-info/RECORD
