Metadata-Version: 2.4
Name: FlowGuide
Version: 0.0.1
Summary: Machine Learning and Optimization Workflows for CFD
Requires-Python: >=3.10
